momentumx/__init__.py
momentumx/_mx.cpython-39-x86_64-linux-gnu.so
momentumx/_mx.pyi
momentumx/cli.py
momentumx-2.7.3.dist-info/LICENSE
momentumx-2.7.3.dist-info/METADATA
momentumx-2.7.3.dist-info/WHEEL
momentumx-2.7.3.dist-info/top_level.txt
momentumx-2.7.3.dist-info/RECORD
