Metadata-Version: 2.1
Name: MomentumX
Version: 2.7.3
Summary: Zero-copy shared memory IPC library for building complex streaming data pipelines capable of processing large datasets
Home-page: https://github.com/captivationsoftware/MomentumX
Author: Captivation Software, LLC
Keywords: shm,shared memory,zero-copy,numpy,big data,scipy,pubsub,pipeline
Requires-Python: >=3.6
Provides-Extra: test
License-File: LICENSE
